{
  "sentence": "Ну, как подумают, что я выбрился для... да непременно же подумают!",
  "tokens": [
    "Ну",
    ",",
    "как",
    "подумают",
    ",",
    "что",
    "я",
    "выбрился",
    "для",
    "...",
    "да",
    "непременно",
    "же",
    "подумают",
    "!"
  ],
  "morphs": [
    [],
    [],
    [
      {
        "word": "как",
        "lexem": "как",
        "tags": "OpencorporaTag('CONJ')"
      },
      {
        "word": "как",
        "lexem": "как",
        "tags": "OpencorporaTag('PRCL')"
      }
    ],
    [
      {
        "word": "подумают",
        "lexem": "подумать",
        "tags": "OpencorporaTag('VERB,perf,intr plur,3per,futr,indc')"
      }
    ],
    [],
    [
      {
        "word": "что",
        "lexem": "что",
        "tags": "OpencorporaTag('NPRO,neut sing,accs')"
      }
    ],
    [
      {
        "word": "я",
        "lexem": "я",
        "tags": "OpencorporaTag('NPRO,1per sing,nomn')"
      }
    ],
    [
      {
        "word": "выбрился",
        "lexem": "выбриться",
        "tags": "OpencorporaTag('VERB,perf,intr masc,sing,past,indc')"
      }
    ],
    [
      {
        "word": "для",
        "lexem": "длить",
        "tags": "OpencorporaTag('GRND,impf,tran pres')"
      }
    ],
    [],
    [],
    [
      {
        "word": "непременно",
        "lexem": "непременно",
        "tags": "OpencorporaTag('ADVB')"
      }
    ],
    [
      {
        "word": "же",
        "lexem": "же",
        "tags": "OpencorporaTag('PRCL')"
      }
    ],
    [
      {
        "word": "подумают",
        "lexem": "подумать",
        "tags": "OpencorporaTag('VERB,perf,intr plur,3per,futr,indc')"
      }
    ],
    []
  ],
  "synts": [
    [
      11,
      12,
      "огранич",
      "непременно",
      "же"
    ],
    [
      7,
      8,
      "обст",
      "выбрился",
      "для"
    ],
    [
      7,
      6,
      "предик",
      "выбрился",
      "я"
    ],
    [
      3,
      5,
      "1-компл",
      "подумают",
      "что"
    ],
    [
      2,
      3,
      "подч-союзн",
      "как",
      "подумают"
    ],
    [
      2,
      3,
      "подч-союзн",
      "как",
      "подумают"
    ],
    [
      5,
      7,
      "подч-союзн",
      "что",
      "выбрился"
    ],
    [
      3,
      13,
      "сочин",
      "подумают",
      "подумают"
    ],
    [
      13,
      11,
      "обст",
      "подумают",
      "непременно"
    ]
  ]
}