{
  "sentence": "Еще минута - и побегут, побегут эти лошади, эти сани по Успенской улице вон из города, в серые снежные поля - и прости, прощай, счастливейшая в жизни неделя!",
  "tokens": [
    "Еще",
    "минута",
    "-",
    "и",
    "побегут",
    ",",
    "побегут",
    "эти",
    "лошади",
    ",",
    "эти",
    "сани",
    "по",
    "Успенской",
    "улице",
    "вон",
    "из",
    "города",
    ",",
    "в",
    "серые",
    "снежные",
    "поля",
    "-",
    "и",
    "прости",
    ",",
    "прощай",
    ",",
    "счастливейшая",
    "в",
    "жизни",
    "неделя",
    "!"
  ],
  "morphs": [
    {
      "index": 0,
      "token": "Еще",
      "homonyms": [
        {
          "index": 0,
          "word": "ещё",
          "lexem": "ещё",
          "tags": "ADV",
          "active": true
        },
        {
          "index": 1,
          "word": "ещё",
          "lexem": "ещё",
          "tags": "PART",
          "active": false
        }
      ]
    },
    {
      "index": 1,
      "token": "минута",
      "homonyms": [
        {
          "index": 0,
          "word": "минута",
          "lexem": "минута",
          "tags": "S ЕД ЖЕН ИМ НЕОД",
          "active": true
        }
      ]
    },
    {
      "index": 2,
      "token": "-",
      "homonyms": [
        {
          "index": 0,
          "word": "-",
          "lexem": "-",
          "tags": "NID",
          "active": false
        }
      ]
    },
    {
      "index": 3,
      "token": "и",
      "homonyms": [
        {
          "index": 0,
          "word": "и",
          "lexem": "и",
          "tags": "CONJ",
          "active": true
        },
        {
          "index": 1,
          "word": "и",
          "lexem": "и",
          "tags": "PART",
          "active": false
        },
        {
          "index": 2,
          "word": "и",
          "lexem": "и",
          "tags": "INTJ",
          "active": false
        },
        {
          "index": 3,
          "word": "и",
          "lexem": "и",
          "tags": "S ЕД МУЖ ИМ ОД",
          "active": false
        },
        {
          "index": 4,
          "word": "и",
          "lexem": "и",
          "tags": "S ЕД МУЖ РОД ОД",
          "active": false
        },
        {
          "index": 5,
          "word": "и",
          "lexem": "и",
          "tags": "S ЕД МУЖ ДАТ ОД",
          "active": false
        },
        {
          "index": 6,
          "word": "и",
          "lexem": "и",
          "tags": "S ЕД МУЖ ВИН ОД",
          "active": false
        },
        {
          "index": 7,
          "word": "и",
          "lexem": "и",
          "tags": "S ЕД МУЖ ТВОР ОД",
          "active": false
        },
        {
          "index": 8,
          "word": "и",
          "lexem": "и",
          "tags": "S ЕД МУЖ ПР ОД",
          "active": false
        },
        {
          "index": 9,
          "word": "и",
          "lexem": "и",
          "tags": "S МН МУЖ ИМ ОД",
          "active": false
        },
        {
          "index": 10,
          "word": "и",
          "lexem": "и",
          "tags": "S МН МУЖ РОД ОД",
          "active": false
        },
        {
          "index": 11,
          "word": "и",
          "lexem": "и",
          "tags": "S МН МУЖ ДАТ ОД",
          "active": false
        },
        {
          "index": 12,
          "word": "и",
          "lexem": "и",
          "tags": "S МН МУЖ ВИН ОД",
          "active": false
        },
        {
          "index": 13,
          "word": "и",
          "lexem": "и",
          "tags": "S МН МУЖ ТВОР ОД",
          "active": false
        },
        {
          "index": 14,
          "word": "и",
          "lexem": "и",
          "tags": "S МН МУЖ ПР ОД",
          "active": false
        }
      ]
    },
    {
      "index": 4,
      "token": "побегут",
      "homonyms": [
        {
          "index": 0,
          "word": "побегут",
          "lexem": "побежать",
          "tags": "V МН СОВ НЕПРОШ ИЗЪЯВ 3-Л",
          "active": true
        }
      ]
    },
    {
      "index": 5,
      "token": ",",
      "homonyms": [
        {
          "index": 0,
          "word": ",",
          "lexem": ",",
          "tags": "NID",
          "active": false
        }
      ]
    },
    {
      "index": 6,
      "token": "побегут",
      "homonyms": [
        {
          "index": 0,
          "word": "побегут",
          "lexem": "побежать",
          "tags": "V МН СОВ НЕПРОШ ИЗЪЯВ 3-Л",
          "active": false
        }
      ]
    },
    {
      "index": 7,
      "token": "эти",
      "homonyms": [
        {
          "index": 0,
          "word": "эти",
          "lexem": "этот",
          "tags": "A МН ИМ",
          "active": true
        },
        {
          "index": 1,
          "word": "эти",
          "lexem": "этот",
          "tags": "A МН ВИН",
          "active": true
        }
      ]
    },
    {
      "index": 8,
      "token": "лошади",
      "homonyms": [
        {
          "index": 0,
          "word": "лошади",
          "lexem": "лошадь",
          "tags": "S ЕД ЖЕН РОД ОД",
          "active": false
        },
        {
          "index": 1,
          "word": "лошади",
          "lexem": "лошадь",
          "tags": "S МН ЖЕН ИМ ОД",
          "active": true
        },
        {
          "index": 2,
          "word": "лошади",
          "lexem": "лошадь",
          "tags": "S ЕД ЖЕН ДАТ ОД",
          "active": false
        },
        {
          "index": 3,
          "word": "лошади",
          "lexem": "лошадь",
          "tags": "S ЕД ЖЕН ПР ОД",
          "active": false
        }
      ]
    },
    {
      "index": 9,
      "token": ",",
      "homonyms": [
        {
          "index": 0,
          "word": ",",
          "lexem": ",",
          "tags": "NID",
          "active": false
        }
      ]
    },
    {
      "index": 10,
      "token": "эти",
      "homonyms": [
        {
          "index": 0,
          "word": "эти",
          "lexem": "этот",
          "tags": "A МН ИМ",
          "active": true
        },
        {
          "index": 1,
          "word": "эти",
          "lexem": "этот",
          "tags": "A МН ВИН",
          "active": true
        }
      ]
    },
    {
      "index": 11,
      "token": "сани",
      "homonyms": [
        {
          "index": 0,
          "word": "сани",
          "lexem": "сани",
          "tags": "S МН ИМ НЕОД",
          "active": true
        },
        {
          "index": 1,
          "word": "сани",
          "lexem": "сани",
          "tags": "S МН ВИН НЕОД",
          "active": true
        },
        {
          "index": 2,
          "word": "сани",
          "lexem": "саня",
          "tags": "S ЕД МУЖ РОД ОД",
          "active": false
        },
        {
          "index": 3,
          "word": "сани",
          "lexem": "саня",
          "tags": "S МН МУЖ ИМ ОД",
          "active": false
        }
      ]
    },
    {
      "index": 12,
      "token": "по",
      "homonyms": [
        {
          "index": 0,
          "word": "по",
          "lexem": "по",
          "tags": "PR",
          "active": true
        },
        {
          "index": 1,
          "word": "по",
          "lexem": "по",
          "tags": "S ЕД СР ИМ НЕОД",
          "active": false
        },
        {
          "index": 2,
          "word": "по",
          "lexem": "по",
          "tags": "S ЕД СР РОД НЕОД",
          "active": false
        },
        {
          "index": 3,
          "word": "по",
          "lexem": "по",
          "tags": "S ЕД СР ДАТ НЕОД",
          "active": false
        },
        {
          "index": 4,
          "word": "по",
          "lexem": "по",
          "tags": "S ЕД СР ВИН НЕОД",
          "active": false
        },
        {
          "index": 5,
          "word": "по",
          "lexem": "по",
          "tags": "S ЕД СР ТВОР НЕОД",
          "active": false
        },
        {
          "index": 6,
          "word": "по",
          "lexem": "по",
          "tags": "S ЕД СР ПР НЕОД",
          "active": false
        },
        {
          "index": 7,
          "word": "по",
          "lexem": "по",
          "tags": "S ЕД ИМ ОД",
          "active": false
        },
        {
          "index": 8,
          "word": "по",
          "lexem": "по",
          "tags": "S ЕД РОД ОД",
          "active": false
        },
        {
          "index": 9,
          "word": "по",
          "lexem": "по",
          "tags": "S ЕД ДАТ ОД",
          "active": false
        },
        {
          "index": 10,
          "word": "по",
          "lexem": "по",
          "tags": "S ЕД ВИН ОД",
          "active": false
        },
        {
          "index": 11,
          "word": "по",
          "lexem": "по",
          "tags": "S ЕД ТВОР ОД",
          "active": false
        },
        {
          "index": 12,
          "word": "по",
          "lexem": "по",
          "tags": "S ЕД ПР ОД",
          "active": false
        },
        {
          "index": 13,
          "word": "по",
          "lexem": "по",
          "tags": "S МН ИМ ОД",
          "active": false
        },
        {
          "index": 14,
          "word": "по",
          "lexem": "по",
          "tags": "S МН РОД ОД",
          "active": false
        },
        {
          "index": 15,
          "word": "по",
          "lexem": "по",
          "tags": "S МН ДАТ ОД",
          "active": false
        },
        {
          "index": 16,
          "word": "по",
          "lexem": "по",
          "tags": "S МН ВИН ОД",
          "active": false
        },
        {
          "index": 17,
          "word": "по",
          "lexem": "по",
          "tags": "S МН ТВОР ОД",
          "active": false
        },
        {
          "index": 18,
          "word": "по",
          "lexem": "по",
          "tags": "S МН ПР ОД",
          "active": false
        }
      ]
    },
    {
      "index": 13,
      "token": "Успенской",
      "homonyms": [
        {
          "index": 0,
          "word": "успенской",
          "lexem": "успенский",
          "tags": "A ЕД ЖЕН РОД",
          "active": false
        },
        {
          "index": 1,
          "word": "успенской",
          "lexem": "успенский",
          "tags": "A ЕД ЖЕН ДАТ",
          "active": false
        },
        {
          "index": 2,
          "word": "успенской",
          "lexem": "успенский",
          "tags": "A ЕД ЖЕН ТВОР",
          "active": false
        },
        {
          "index": 3,
          "word": "успенской",
          "lexem": "успенский",
          "tags": "A ЕД ЖЕН ПР",
          "active": false
        },
        {
          "index": 4,
          "word": "успенской",
          "lexem": "успенский",
          "tags": "S ЕД ЖЕН РОД ОД",
          "active": true
        },
        {
          "index": 5,
          "word": "успенской",
          "lexem": "успенский",
          "tags": "S ЕД ЖЕН ДАТ ОД",
          "active": true
        },
        {
          "index": 6,
          "word": "успенской",
          "lexem": "успенский",
          "tags": "S ЕД ЖЕН ТВОР ОД",
          "active": true
        },
        {
          "index": 7,
          "word": "успенской",
          "lexem": "успенский",
          "tags": "S ЕД ЖЕН ПР ОД",
          "active": true
        }
      ]
    },
    {
      "index": 14,
      "token": "улице",
      "homonyms": [
        {
          "index": 0,
          "word": "улице",
          "lexem": "улица",
          "tags": "S ЕД ЖЕН ПР НЕОД",
          "active": true
        },
        {
          "index": 1,
          "word": "улице",
          "lexem": "улица",
          "tags": "S ЕД ЖЕН ДАТ НЕОД",
          "active": true
        }
      ]
    },
    {
      "index": 15,
      "token": "вон",
      "homonyms": [
        {
          "index": 0,
          "word": "вон",
          "lexem": "вон",
          "tags": "ADV",
          "active": false
        },
        {
          "index": 1,
          "word": "вон",
          "lexem": "вон",
          "tags": "PART",
          "active": false
        },
        {
          "index": 2,
          "word": "вон",
          "lexem": "вона",
          "tags": "S МН ЖЕН РОД НЕОД",
          "active": true
        }
      ]
    },
    {
      "index": 16,
      "token": "из",
      "homonyms": [
        {
          "index": 0,
          "word": "из",
          "lexem": "из",
          "tags": "PR",
          "active": true
        },
        {
          "index": 1,
          "word": "из",
          "lexem": "иза",
          "tags": "S МН ЖЕН РОД ОД",
          "active": false
        },
        {
          "index": 2,
          "word": "из",
          "lexem": "иза",
          "tags": "S МН ЖЕН ВИН ОД",
          "active": false
        }
      ]
    },
    {
      "index": 17,
      "token": "города",
      "homonyms": [
        {
          "index": 0,
          "word": "города",
          "lexem": "город",
          "tags": "S ЕД МУЖ РОД НЕОД",
          "active": true
        },
        {
          "index": 1,
          "word": "города",
          "lexem": "город",
          "tags": "S МН МУЖ ИМ НЕОД",
          "active": false
        },
        {
          "index": 2,
          "word": "города",
          "lexem": "город",
          "tags": "S МН МУЖ ВИН НЕОД",
          "active": true
        }
      ]
    },
    {
      "index": 18,
      "token": ",",
      "homonyms": [
        {
          "index": 0,
          "word": ",",
          "lexem": ",",
          "tags": "NID",
          "active": false
        }
      ]
    },
    {
      "index": 19,
      "token": "в",
      "homonyms": [
        {
          "index": 0,
          "word": "в",
          "lexem": "в",
          "tags": "PR",
          "active": true
        },
        {
          "index": 1,
          "word": "в",
          "lexem": "в",
          "tags": "S ЕД МУЖ РОД НЕОД",
          "active": false
        },
        {
          "index": 2,
          "word": "в",
          "lexem": "в",
          "tags": "S ЕД МУЖ ПР НЕОД",
          "active": false
        },
        {
          "index": 3,
          "word": "в",
          "lexem": "в",
          "tags": "S ЕД МУЖ ИМ НЕОД",
          "active": false
        },
        {
          "index": 4,
          "word": "в",
          "lexem": "в",
          "tags": "S ЕД МУЖ ДАТ НЕОД",
          "active": false
        },
        {
          "index": 5,
          "word": "в",
          "lexem": "в",
          "tags": "S ЕД МУЖ ВИН НЕОД",
          "active": false
        },
        {
          "index": 6,
          "word": "в",
          "lexem": "в",
          "tags": "S ЕД МУЖ ТВОР НЕОД",
          "active": false
        },
        {
          "index": 7,
          "word": "в",
          "lexem": "в",
          "tags": "S МН МУЖ ИМ НЕОД",
          "active": false
        },
        {
          "index": 8,
          "word": "в",
          "lexem": "в",
          "tags": "S МН МУЖ РОД НЕОД",
          "active": false
        },
        {
          "index": 9,
          "word": "в",
          "lexem": "в",
          "tags": "S МН МУЖ ДАТ НЕОД",
          "active": false
        },
        {
          "index": 10,
          "word": "в",
          "lexem": "в",
          "tags": "S МН МУЖ ВИН НЕОД",
          "active": false
        },
        {
          "index": 11,
          "word": "в",
          "lexem": "в",
          "tags": "S МН МУЖ ТВОР НЕОД",
          "active": false
        },
        {
          "index": 12,
          "word": "в",
          "lexem": "в",
          "tags": "S МН МУЖ ПР НЕОД",
          "active": false
        }
      ]
    },
    {
      "index": 20,
      "token": "серые",
      "homonyms": [
        {
          "index": 0,
          "word": "серые",
          "lexem": "серый",
          "tags": "A МН ИМ",
          "active": true
        },
        {
          "index": 1,
          "word": "серые",
          "lexem": "серый",
          "tags": "A МН ВИН",
          "active": true
        }
      ]
    },
    {
      "index": 21,
      "token": "снежные",
      "homonyms": [
        {
          "index": 0,
          "word": "снежные",
          "lexem": "снежный",
          "tags": "A МН ИМ",
          "active": true
        },
        {
          "index": 1,
          "word": "снежные",
          "lexem": "снежный",
          "tags": "A МН ВИН",
          "active": true
        }
      ]
    },
    {
      "index": 22,
      "token": "поля",
      "homonyms": [
        {
          "index": 0,
          "word": "поля",
          "lexem": "поле",
          "tags": "S ЕД СР РОД НЕОД",
          "active": false
        },
        {
          "index": 1,
          "word": "поля",
          "lexem": "поле",
          "tags": "S МН СР ИМ НЕОД",
          "active": true
        },
        {
          "index": 2,
          "word": "поля",
          "lexem": "поле",
          "tags": "S МН СР ВИН НЕОД",
          "active": true
        },
        {
          "index": 3,
          "word": "поля",
          "lexem": "поль",
          "tags": "S ЕД МУЖ РОД ОД",
          "active": false
        },
        {
          "index": 4,
          "word": "поля",
          "lexem": "поль",
          "tags": "S ЕД МУЖ ВИН ОД",
          "active": false
        },
        {
          "index": 5,
          "word": "поля",
          "lexem": "поля",
          "tags": "S ЕД ЖЕН ИМ ОД",
          "active": false
        },
        {
          "index": 6,
          "word": "поля",
          "lexem": "полоть",
          "tags": "V ДЕЕПР НЕСОВ НЕПРОШ",
          "active": false
        }
      ]
    },
    {
      "index": 23,
      "token": "-",
      "homonyms": [
        {
          "index": 0,
          "word": "-",
          "lexem": "-",
          "tags": "NID",
          "active": false
        }
      ]
    },
    {
      "index": 24,
      "token": "и",
      "homonyms": [
        {
          "index": 0,
          "word": "и",
          "lexem": "и",
          "tags": "CONJ",
          "active": true
        },
        {
          "index": 1,
          "word": "и",
          "lexem": "и",
          "tags": "PART",
          "active": false
        },
        {
          "index": 2,
          "word": "и",
          "lexem": "и",
          "tags": "INTJ",
          "active": false
        },
        {
          "index": 3,
          "word": "и",
          "lexem": "и",
          "tags": "S ЕД МУЖ ИМ ОД",
          "active": false
        },
        {
          "index": 4,
          "word": "и",
          "lexem": "и",
          "tags": "S ЕД МУЖ РОД ОД",
          "active": false
        },
        {
          "index": 5,
          "word": "и",
          "lexem": "и",
          "tags": "S ЕД МУЖ ДАТ ОД",
          "active": false
        },
        {
          "index": 6,
          "word": "и",
          "lexem": "и",
          "tags": "S ЕД МУЖ ВИН ОД",
          "active": false
        },
        {
          "index": 7,
          "word": "и",
          "lexem": "и",
          "tags": "S ЕД МУЖ ТВОР ОД",
          "active": false
        },
        {
          "index": 8,
          "word": "и",
          "lexem": "и",
          "tags": "S ЕД МУЖ ПР ОД",
          "active": false
        },
        {
          "index": 9,
          "word": "и",
          "lexem": "и",
          "tags": "S МН МУЖ ИМ ОД",
          "active": false
        },
        {
          "index": 10,
          "word": "и",
          "lexem": "и",
          "tags": "S МН МУЖ РОД ОД",
          "active": false
        },
        {
          "index": 11,
          "word": "и",
          "lexem": "и",
          "tags": "S МН МУЖ ДАТ ОД",
          "active": false
        },
        {
          "index": 12,
          "word": "и",
          "lexem": "и",
          "tags": "S МН МУЖ ВИН ОД",
          "active": false
        },
        {
          "index": 13,
          "word": "и",
          "lexem": "и",
          "tags": "S МН МУЖ ТВОР ОД",
          "active": false
        },
        {
          "index": 14,
          "word": "и",
          "lexem": "и",
          "tags": "S МН МУЖ ПР ОД",
          "active": false
        }
      ]
    },
    {
      "index": 25,
      "token": "прости",
      "homonyms": [
        {
          "index": 0,
          "word": "прости",
          "lexem": "простить",
          "tags": "V ЕД СОВ ПОВ",
          "active": true
        }
      ]
    },
    {
      "index": 26,
      "token": ",",
      "homonyms": [
        {
          "index": 0,
          "word": ",",
          "lexem": ",",
          "tags": "NID",
          "active": false
        }
      ]
    },
    {
      "index": 27,
      "token": "прощай",
      "homonyms": [
        {
          "index": 0,
          "word": "прощай",
          "lexem": "прощать",
          "tags": "V ЕД НЕСОВ ПОВ",
          "active": false
        }
      ]
    },
    {
      "index": 28,
      "token": ",",
      "homonyms": [
        {
          "index": 0,
          "word": ",",
          "lexem": ",",
          "tags": "NID",
          "active": false
        }
      ]
    },
    {
      "index": 29,
      "token": "счастливейшая",
      "homonyms": [
        {
          "index": 0,
          "word": "счастливейшая",
          "lexem": "счастливый",
          "tags": "A ЕД ЖЕН ИМ",
          "active": true
        }
      ]
    },
    {
      "index": 30,
      "token": "в",
      "homonyms": [
        {
          "index": 0,
          "word": "в",
          "lexem": "в",
          "tags": "PR",
          "active": true
        },
        {
          "index": 1,
          "word": "в",
          "lexem": "в",
          "tags": "S ЕД МУЖ РОД НЕОД",
          "active": false
        },
        {
          "index": 2,
          "word": "в",
          "lexem": "в",
          "tags": "S ЕД МУЖ ПР НЕОД",
          "active": false
        },
        {
          "index": 3,
          "word": "в",
          "lexem": "в",
          "tags": "S ЕД МУЖ ИМ НЕОД",
          "active": false
        },
        {
          "index": 4,
          "word": "в",
          "lexem": "в",
          "tags": "S ЕД МУЖ ДАТ НЕОД",
          "active": false
        },
        {
          "index": 5,
          "word": "в",
          "lexem": "в",
          "tags": "S ЕД МУЖ ВИН НЕОД",
          "active": false
        },
        {
          "index": 6,
          "word": "в",
          "lexem": "в",
          "tags": "S ЕД МУЖ ТВОР НЕОД",
          "active": false
        },
        {
          "index": 7,
          "word": "в",
          "lexem": "в",
          "tags": "S МН МУЖ ИМ НЕОД",
          "active": false
        },
        {
          "index": 8,
          "word": "в",
          "lexem": "в",
          "tags": "S МН МУЖ РОД НЕОД",
          "active": false
        },
        {
          "index": 9,
          "word": "в",
          "lexem": "в",
          "tags": "S МН МУЖ ДАТ НЕОД",
          "active": false
        },
        {
          "index": 10,
          "word": "в",
          "lexem": "в",
          "tags": "S МН МУЖ ВИН НЕОД",
          "active": false
        },
        {
          "index": 11,
          "word": "в",
          "lexem": "в",
          "tags": "S МН МУЖ ТВОР НЕОД",
          "active": false
        },
        {
          "index": 12,
          "word": "в",
          "lexem": "в",
          "tags": "S МН МУЖ ПР НЕОД",
          "active": false
        }
      ]
    },
    {
      "index": 31,
      "token": "жизни",
      "homonyms": [
        {
          "index": 0,
          "word": "жизни",
          "lexem": "жизнь",
          "tags": "S ЕД ЖЕН РОД НЕОД",
          "active": true
        },
        {
          "index": 1,
          "word": "жизни",
          "lexem": "жизнь",
          "tags": "S ЕД ЖЕН ПР НЕОД",
          "active": true
        },
        {
          "index": 2,
          "word": "жизни",
          "lexem": "жизнь",
          "tags": "S ЕД ЖЕН ДАТ НЕОД",
          "active": true
        },
        {
          "index": 3,
          "word": "жизни",
          "lexem": "жизнь",
          "tags": "S МН ЖЕН ВИН НЕОД",
          "active": true
        },
        {
          "index": 4,
          "word": "жизни",
          "lexem": "жизнь",
          "tags": "S МН ЖЕН ИМ НЕОД",
          "active": true
        }
      ]
    },
    {
      "index": 32,
      "token": "неделя",
      "homonyms": [
        {
          "index": 0,
          "word": "неделя",
          "lexem": "неделя",
          "tags": "S ЕД ЖЕН ИМ НЕОД",
          "active": true
        }
      ]
    },
    {
      "index": 33,
      "token": "!",
      "homonyms": [
        {
          "index": 0,
          "word": "!",
          "lexem": "!",
          "tags": "NID",
          "active": false
        }
      ]
    }
  ],
  "synts": [
    {
      "dep_type": "опред",
      "head": "поля",
      "dependent": "серые",
      "head_i": 22,
      "head_homonym_i": 1,
      "dependent_i": 20,
      "dependent_homonym_i": 0
    },
    {
      "dep_type": "опред",
      "head": "поля",
      "dependent": "серые",
      "head_i": 22,
      "head_homonym_i": 2,
      "dependent_i": 20,
      "dependent_homonym_i": 1
    },
    {
      "dep_type": "опред",
      "head": "поля",
      "dependent": "снежные",
      "head_i": 22,
      "head_homonym_i": 1,
      "dependent_i": 21,
      "dependent_homonym_i": 0
    },
    {
      "dep_type": "опред",
      "head": "поля",
      "dependent": "снежные",
      "head_i": 22,
      "head_homonym_i": 2,
      "dependent_i": 21,
      "dependent_homonym_i": 1
    },
    {
      "dep_type": "опред",
      "head": "сани",
      "dependent": "эти",
      "head_i": 11,
      "head_homonym_i": 0,
      "dependent_i": 10,
      "dependent_homonym_i": 0
    },
    {
      "dep_type": "опред",
      "head": "сани",
      "dependent": "эти",
      "head_i": 11,
      "head_homonym_i": 1,
      "dependent_i": 10,
      "dependent_homonym_i": 1
    },
    {
      "dep_type": "аппоз",
      "head": "сани",
      "dependent": "успенской",
      "head_i": 11,
      "head_homonym_i": 0,
      "dependent_i": 13,
      "dependent_homonym_i": 4
    },
    {
      "dep_type": "аппоз",
      "head": "сани",
      "dependent": "успенской",
      "head_i": 11,
      "head_homonym_i": 0,
      "dependent_i": 13,
      "dependent_homonym_i": 5
    },
    {
      "dep_type": "аппоз",
      "head": "сани",
      "dependent": "успенской",
      "head_i": 11,
      "head_homonym_i": 0,
      "dependent_i": 13,
      "dependent_homonym_i": 6
    },
    {
      "dep_type": "аппоз",
      "head": "сани",
      "dependent": "успенской",
      "head_i": 11,
      "head_homonym_i": 0,
      "dependent_i": 13,
      "dependent_homonym_i": 7
    },
    {
      "dep_type": "аппоз",
      "head": "сани",
      "dependent": "успенской",
      "head_i": 11,
      "head_homonym_i": 1,
      "dependent_i": 13,
      "dependent_homonym_i": 4
    },
    {
      "dep_type": "аппоз",
      "head": "сани",
      "dependent": "успенской",
      "head_i": 11,
      "head_homonym_i": 1,
      "dependent_i": 13,
      "dependent_homonym_i": 5
    },
    {
      "dep_type": "аппоз",
      "head": "сани",
      "dependent": "успенской",
      "head_i": 11,
      "head_homonym_i": 1,
      "dependent_i": 13,
      "dependent_homonym_i": 6
    },
    {
      "dep_type": "аппоз",
      "head": "сани",
      "dependent": "успенской",
      "head_i": 11,
      "head_homonym_i": 1,
      "dependent_i": 13,
      "dependent_homonym_i": 7
    },
    {
      "dep_type": "элект",
      "head": "вон",
      "dependent": "из",
      "head_i": 15,
      "head_homonym_i": 2,
      "dependent_i": 16,
      "dependent_homonym_i": 0
    },
    {
      "dep_type": "предл",
      "head": "по",
      "dependent": "успенской",
      "head_i": 12,
      "head_homonym_i": 0,
      "dependent_i": 13,
      "dependent_homonym_i": 5
    },
    {
      "dep_type": "предл",
      "head": "из",
      "dependent": "города",
      "head_i": 16,
      "head_homonym_i": 0,
      "dependent_i": 17,
      "dependent_homonym_i": 0
    },
    {
      "dep_type": "предл",
      "head": "в",
      "dependent": "поля",
      "head_i": 19,
      "head_homonym_i": 0,
      "dependent_i": 22,
      "dependent_homonym_i": 1
    },
    {
      "dep_type": "предл",
      "head": "в",
      "dependent": "поля",
      "head_i": 19,
      "head_homonym_i": 0,
      "dependent_i": 22,
      "dependent_homonym_i": 2
    },
    {
      "dep_type": "предл",
      "head": "в",
      "dependent": "жизни",
      "head_i": 30,
      "head_homonym_i": 0,
      "dependent_i": 31,
      "dependent_homonym_i": 1
    },
    {
      "dep_type": "предл",
      "head": "в",
      "dependent": "жизни",
      "head_i": 30,
      "head_homonym_i": 0,
      "dependent_i": 31,
      "dependent_homonym_i": 3
    },
    {
      "dep_type": "предл",
      "head": "в",
      "dependent": "жизни",
      "head_i": 30,
      "head_homonym_i": 0,
      "dependent_i": 31,
      "dependent_homonym_i": 4
    },
    {
      "dep_type": "об-аппоз",
      "head": "лошади",
      "dependent": "сани",
      "head_i": 8,
      "head_homonym_i": 1,
      "dependent_i": 11,
      "dependent_homonym_i": 0
    },
    {
      "dep_type": "атриб",
      "head": "сани",
      "dependent": "по",
      "head_i": 11,
      "head_homonym_i": 0,
      "dependent_i": 12,
      "dependent_homonym_i": 0
    },
    {
      "dep_type": "атриб",
      "head": "сани",
      "dependent": "по",
      "head_i": 11,
      "head_homonym_i": 1,
      "dependent_i": 12,
      "dependent_homonym_i": 0
    },
    {
      "dep_type": "атриб",
      "head": "успенской",
      "dependent": "вон",
      "head_i": 13,
      "head_homonym_i": 5,
      "dependent_i": 15,
      "dependent_homonym_i": 2
    },
    {
      "dep_type": "атриб",
      "head": "успенской",
      "dependent": "вон",
      "head_i": 13,
      "head_homonym_i": 6,
      "dependent_i": 15,
      "dependent_homonym_i": 2
    },
    {
      "dep_type": "атриб",
      "head": "успенской",
      "dependent": "вон",
      "head_i": 13,
      "head_homonym_i": 7,
      "dependent_i": 15,
      "dependent_homonym_i": 2
    },
    {
      "dep_type": "атриб",
      "head": "улице",
      "dependent": "вон",
      "head_i": 14,
      "head_homonym_i": 0,
      "dependent_i": 15,
      "dependent_homonym_i": 2
    },
    {
      "dep_type": "атриб",
      "head": "улице",
      "dependent": "вон",
      "head_i": 14,
      "head_homonym_i": 1,
      "dependent_i": 15,
      "dependent_homonym_i": 2
    },
    {
      "dep_type": "атриб",
      "head": "вон",
      "dependent": "из",
      "head_i": 15,
      "head_homonym_i": 2,
      "dependent_i": 16,
      "dependent_homonym_i": 0
    },
    {
      "dep_type": "атриб",
      "head": "счастливейшая",
      "dependent": "в",
      "head_i": 29,
      "head_homonym_i": 0,
      "dependent_i": 30,
      "dependent_homonym_i": 0
    },
    {
      "dep_type": "предик",
      "head": "побегут",
      "dependent": "лошади",
      "head_i": 4,
      "head_homonym_i": 0,
      "dependent_i": 8,
      "dependent_homonym_i": 1
    },
    {
      "dep_type": "предик",
      "head": "прости",
      "dependent": "минута",
      "head_i": 25,
      "head_homonym_i": 0,
      "dependent_i": 1,
      "dependent_homonym_i": 0
    },
    {
      "dep_type": "предик",
      "head": "прости",
      "dependent": "неделя",
      "head_i": 25,
      "head_homonym_i": 0,
      "dependent_i": 32,
      "dependent_homonym_i": 0
    },
    {
      "dep_type": "1-компл",
      "head": "побегут",
      "dependent": "эти",
      "head_i": 4,
      "head_homonym_i": 0,
      "dependent_i": 7,
      "dependent_homonym_i": 1
    },
    {
      "dep_type": "1-компл",
      "head": "побегут",
      "dependent": "сани",
      "head_i": 4,
      "head_homonym_i": 0,
      "dependent_i": 11,
      "dependent_homonym_i": 1
    },
    {
      "dep_type": "1-компл",
      "head": "побегут",
      "dependent": "улице",
      "head_i": 4,
      "head_homonym_i": 0,
      "dependent_i": 14,
      "dependent_homonym_i": 1
    },
    {
      "dep_type": "1-компл",
      "head": "прости",
      "dependent": "в",
      "head_i": 25,
      "head_homonym_i": 0,
      "dependent_i": 19,
      "dependent_homonym_i": 0
    },
    {
      "dep_type": "соч-союзн",
      "head": "и",
      "dependent": "побегут",
      "head_i": 3,
      "head_homonym_i": 0,
      "dependent_i": 4,
      "dependent_homonym_i": 0
    },
    {
      "dep_type": "соч-союзн",
      "head": "и",
      "dependent": "прости",
      "head_i": 24,
      "head_homonym_i": 0,
      "dependent_i": 25,
      "dependent_homonym_i": 0
    },
    {
      "dep_type": "соч-союзн",
      "head": "и",
      "dependent": "эти",
      "head_i": 3,
      "head_homonym_i": 0,
      "dependent_i": 7,
      "dependent_homonym_i": 0
    },
    {
      "dep_type": "соч-союзн",
      "head": "и",
      "dependent": "эти",
      "head_i": 3,
      "head_homonym_i": 0,
      "dependent_i": 7,
      "dependent_homonym_i": 1
    },
    {
      "dep_type": "соч-союзн",
      "head": "и",
      "dependent": "эти",
      "head_i": 3,
      "head_homonym_i": 0,
      "dependent_i": 10,
      "dependent_homonym_i": 0
    },
    {
      "dep_type": "соч-союзн",
      "head": "и",
      "dependent": "эти",
      "head_i": 3,
      "head_homonym_i": 0,
      "dependent_i": 10,
      "dependent_homonym_i": 1
    },
    {
      "dep_type": "соч-союзн",
      "head": "и",
      "dependent": "сани",
      "head_i": 3,
      "head_homonym_i": 0,
      "dependent_i": 11,
      "dependent_homonym_i": 0
    },
    {
      "dep_type": "соч-союзн",
      "head": "и",
      "dependent": "сани",
      "head_i": 3,
      "head_homonym_i": 0,
      "dependent_i": 11,
      "dependent_homonym_i": 1
    },
    {
      "dep_type": "соч-союзн",
      "head": "и",
      "dependent": "успенской",
      "head_i": 3,
      "head_homonym_i": 0,
      "dependent_i": 13,
      "dependent_homonym_i": 4
    },
    {
      "dep_type": "соч-союзн",
      "head": "и",
      "dependent": "успенской",
      "head_i": 3,
      "head_homonym_i": 0,
      "dependent_i": 13,
      "dependent_homonym_i": 5
    },
    {
      "dep_type": "соч-союзн",
      "head": "и",
      "dependent": "успенской",
      "head_i": 3,
      "head_homonym_i": 0,
      "dependent_i": 13,
      "dependent_homonym_i": 6
    },
    {
      "dep_type": "соч-союзн",
      "head": "и",
      "dependent": "успенской",
      "head_i": 3,
      "head_homonym_i": 0,
      "dependent_i": 13,
      "dependent_homonym_i": 7
    },
    {
      "dep_type": "соч-союзн",
      "head": "и",
      "dependent": "улице",
      "head_i": 3,
      "head_homonym_i": 0,
      "dependent_i": 14,
      "dependent_homonym_i": 0
    },
    {
      "dep_type": "соч-союзн",
      "head": "и",
      "dependent": "улице",
      "head_i": 3,
      "head_homonym_i": 0,
      "dependent_i": 14,
      "dependent_homonym_i": 1
    },
    {
      "dep_type": "соч-союзн",
      "head": "и",
      "dependent": "вон",
      "head_i": 3,
      "head_homonym_i": 0,
      "dependent_i": 15,
      "dependent_homonym_i": 2
    },
    {
      "dep_type": "соч-союзн",
      "head": "и",
      "dependent": "города",
      "head_i": 3,
      "head_homonym_i": 0,
      "dependent_i": 17,
      "dependent_homonym_i": 0
    },
    {
      "dep_type": "соч-союзн",
      "head": "и",
      "dependent": "города",
      "head_i": 3,
      "head_homonym_i": 0,
      "dependent_i": 17,
      "dependent_homonym_i": 2
    },
    {
      "dep_type": "соч-союзн",
      "head": "и",
      "dependent": "серые",
      "head_i": 3,
      "head_homonym_i": 0,
      "dependent_i": 20,
      "dependent_homonym_i": 0
    },
    {
      "dep_type": "соч-союзн",
      "head": "и",
      "dependent": "серые",
      "head_i": 3,
      "head_homonym_i": 0,
      "dependent_i": 20,
      "dependent_homonym_i": 1
    },
    {
      "dep_type": "соч-союзн",
      "head": "и",
      "dependent": "снежные",
      "head_i": 3,
      "head_homonym_i": 0,
      "dependent_i": 21,
      "dependent_homonym_i": 0
    },
    {
      "dep_type": "соч-союзн",
      "head": "и",
      "dependent": "снежные",
      "head_i": 3,
      "head_homonym_i": 0,
      "dependent_i": 21,
      "dependent_homonym_i": 1
    },
    {
      "dep_type": "соч-союзн",
      "head": "и",
      "dependent": "счастливейшая",
      "head_i": 24,
      "head_homonym_i": 0,
      "dependent_i": 29,
      "dependent_homonym_i": 0
    },
    {
      "dep_type": "соч-союзн",
      "head": "и",
      "dependent": "жизни",
      "head_i": 24,
      "head_homonym_i": 0,
      "dependent_i": 31,
      "dependent_homonym_i": 0
    },
    {
      "dep_type": "соч-союзн",
      "head": "и",
      "dependent": "жизни",
      "head_i": 24,
      "head_homonym_i": 0,
      "dependent_i": 31,
      "dependent_homonym_i": 1
    },
    {
      "dep_type": "соч-союзн",
      "head": "и",
      "dependent": "жизни",
      "head_i": 24,
      "head_homonym_i": 0,
      "dependent_i": 31,
      "dependent_homonym_i": 2
    },
    {
      "dep_type": "соч-союзн",
      "head": "и",
      "dependent": "жизни",
      "head_i": 24,
      "head_homonym_i": 0,
      "dependent_i": 31,
      "dependent_homonym_i": 3
    },
    {
      "dep_type": "соч-союзн",
      "head": "и",
      "dependent": "жизни",
      "head_i": 24,
      "head_homonym_i": 0,
      "dependent_i": 31,
      "dependent_homonym_i": 4
    },
    {
      "dep_type": "сочин",
      "head": "побегут",
      "dependent": "и",
      "head_i": 4,
      "head_homonym_i": 0,
      "dependent_i": 24,
      "dependent_homonym_i": 0
    },
    {
      "dep_type": "обст",
      "head": "побегут",
      "dependent": "ещё",
      "head_i": 4,
      "head_homonym_i": 0,
      "dependent_i": 0,
      "dependent_homonym_i": 0
    }
  ]
}