{
  "sentence": "Вообще в таком деле трудно судить.",
  "tokens": [
    "Вообще",
    "в",
    "таком",
    "деле",
    "трудно",
    "судить",
    "."
  ],
  "morphs": [
    {
      "index": 0,
      "token": "Вообще",
      "homonyms": [
        {
          "index": 0,
          "word": "вообще",
          "lexem": "вообще",
          "tags": "ADV",
          "active": true
        },
        {
          "index": 1,
          "word": "вообще",
          "lexem": "вообще",
          "tags": "CONJ",
          "active": false
        }
      ]
    },
    {
      "index": 1,
      "token": "в",
      "homonyms": [
        {
          "index": 0,
          "word": "в",
          "lexem": "в",
          "tags": "PR",
          "active": true
        },
        {
          "index": 1,
          "word": "в",
          "lexem": "в",
          "tags": "S ЕД МУЖ РОД НЕОД",
          "active": false
        },
        {
          "index": 2,
          "word": "в",
          "lexem": "в",
          "tags": "S ЕД МУЖ ПР НЕОД",
          "active": false
        },
        {
          "index": 3,
          "word": "в",
          "lexem": "в",
          "tags": "S ЕД МУЖ ИМ НЕОД",
          "active": false
        },
        {
          "index": 4,
          "word": "в",
          "lexem": "в",
          "tags": "S ЕД МУЖ ДАТ НЕОД",
          "active": false
        },
        {
          "index": 5,
          "word": "в",
          "lexem": "в",
          "tags": "S ЕД МУЖ ВИН НЕОД",
          "active": false
        },
        {
          "index": 6,
          "word": "в",
          "lexem": "в",
          "tags": "S ЕД МУЖ ТВОР НЕОД",
          "active": false
        },
        {
          "index": 7,
          "word": "в",
          "lexem": "в",
          "tags": "S МН МУЖ ИМ НЕОД",
          "active": false
        },
        {
          "index": 8,
          "word": "в",
          "lexem": "в",
          "tags": "S МН МУЖ РОД НЕОД",
          "active": false
        },
        {
          "index": 9,
          "word": "в",
          "lexem": "в",
          "tags": "S МН МУЖ ДАТ НЕОД",
          "active": false
        },
        {
          "index": 10,
          "word": "в",
          "lexem": "в",
          "tags": "S МН МУЖ ВИН НЕОД",
          "active": false
        },
        {
          "index": 11,
          "word": "в",
          "lexem": "в",
          "tags": "S МН МУЖ ТВОР НЕОД",
          "active": false
        },
        {
          "index": 12,
          "word": "в",
          "lexem": "в",
          "tags": "S МН МУЖ ПР НЕОД",
          "active": false
        }
      ]
    },
    {
      "index": 2,
      "token": "таком",
      "homonyms": [
        {
          "index": 0,
          "word": "таком",
          "lexem": "такой",
          "tags": "A ЕД МУЖ ПР",
          "active": false
        },
        {
          "index": 1,
          "word": "таком",
          "lexem": "такой",
          "tags": "A ЕД СР ПР",
          "active": true
        }
      ]
    },
    {
      "index": 3,
      "token": "деле",
      "homonyms": [
        {
          "index": 0,
          "word": "деле",
          "lexem": "дело",
          "tags": "S ЕД СР ПР НЕОД",
          "active": true
        }
      ]
    },
    {
      "index": 4,
      "token": "трудно",
      "homonyms": [
        {
          "index": 0,
          "word": "трудно",
          "lexem": "трудно",
          "tags": "ADV",
          "active": true
        },
        {
          "index": 1,
          "word": "трудно",
          "lexem": "трудный",
          "tags": "A КР ЕД СР",
          "active": true
        }
      ]
    },
    {
      "index": 5,
      "token": "судить",
      "homonyms": [
        {
          "index": 0,
          "word": "судить",
          "lexem": "судить",
          "tags": "V ИНФ НЕСОВ",
          "active": true
        }
      ]
    },
    {
      "index": 6,
      "token": ".",
      "homonyms": [
        {
          "index": 0,
          "word": ".",
          "lexem": ".",
          "tags": "NID",
          "active": false
        }
      ]
    }
  ],
  "synts": [
    {
      "dep_type": "опред",
      "head": "деле",
      "dependent": "таком",
      "head_i": 3,
      "head_homonym_i": 0,
      "dependent_i": 2,
      "dependent_homonym_i": 1
    },
    {
      "dep_type": "предл",
      "head": "в",
      "dependent": "деле",
      "head_i": 1,
      "head_homonym_i": 0,
      "dependent_i": 3,
      "dependent_homonym_i": 0
    },
    {
      "dep_type": "предик",
      "head": "трудно",
      "dependent": "судить",
      "head_i": 4,
      "head_homonym_i": 1,
      "dependent_i": 5,
      "dependent_homonym_i": 0
    },
    {
      "dep_type": "1-компл",
      "head": "трудно",
      "dependent": "в",
      "head_i": 4,
      "head_homonym_i": 1,
      "dependent_i": 1,
      "dependent_homonym_i": 0
    },
    {
      "dep_type": "обст",
      "head": "трудно",
      "dependent": "вообще",
      "head_i": 4,
      "head_homonym_i": 1,
      "dependent_i": 0,
      "dependent_homonym_i": 0
    },
    {
      "dep_type": "обст",
      "head": "трудно",
      "dependent": "в",
      "head_i": 4,
      "head_homonym_i": 1,
      "dependent_i": 1,
      "dependent_homonym_i": 0
    },
    {
      "dep_type": "обст",
      "head": "судить",
      "dependent": "трудно",
      "head_i": 5,
      "head_homonym_i": 0,
      "dependent_i": 4,
      "dependent_homonym_i": 0
    }
  ]
}