{
  "sentence": "Проснулся ли он, однако?",
  "tokens": [
    "Проснулся",
    "ли",
    "он",
    ",",
    "однако",
    "?"
  ],
  "morphs": [
    {
      "index": 0,
      "token": "Проснулся",
      "homonyms": [
        {
          "index": 0,
          "word": "проснулся",
          "lexem": "проснуться",
          "tags": "V ЕД СОВ ПРОШ ИЗЪЯВ",
          "active": true
        }
      ]
    },
    {
      "index": 1,
      "token": "ли",
      "homonyms": [
        {
          "index": 0,
          "word": "ли",
          "lexem": "ли",
          "tags": "CONJ",
          "active": false
        },
        {
          "index": 1,
          "word": "ли",
          "lexem": "ли",
          "tags": "PART",
          "active": false
        },
        {
          "index": 2,
          "word": "ли",
          "lexem": "ли",
          "tags": "S ЕД МУЖ ИМ ОД",
          "active": false
        },
        {
          "index": 3,
          "word": "ли",
          "lexem": "ли",
          "tags": "S ЕД МУЖ РОД ОД",
          "active": false
        },
        {
          "index": 4,
          "word": "ли",
          "lexem": "ли",
          "tags": "S ЕД МУЖ ДАТ ОД",
          "active": false
        },
        {
          "index": 5,
          "word": "ли",
          "lexem": "ли",
          "tags": "S ЕД МУЖ ВИН ОД",
          "active": false
        },
        {
          "index": 6,
          "word": "ли",
          "lexem": "ли",
          "tags": "S ЕД МУЖ ТВОР ОД",
          "active": false
        },
        {
          "index": 7,
          "word": "ли",
          "lexem": "ли",
          "tags": "S ЕД МУЖ ПР ОД",
          "active": false
        },
        {
          "index": 8,
          "word": "ли",
          "lexem": "ли",
          "tags": "S ЕД ИМ ОД",
          "active": false
        },
        {
          "index": 9,
          "word": "ли",
          "lexem": "ли",
          "tags": "S ЕД РОД ОД",
          "active": false
        },
        {
          "index": 10,
          "word": "ли",
          "lexem": "ли",
          "tags": "S ЕД ДАТ ОД",
          "active": false
        },
        {
          "index": 11,
          "word": "ли",
          "lexem": "ли",
          "tags": "S ЕД ВИН ОД",
          "active": false
        },
        {
          "index": 12,
          "word": "ли",
          "lexem": "ли",
          "tags": "S ЕД ТВОР ОД",
          "active": false
        },
        {
          "index": 13,
          "word": "ли",
          "lexem": "ли",
          "tags": "S ЕД ПР ОД",
          "active": false
        },
        {
          "index": 14,
          "word": "ли",
          "lexem": "ли",
          "tags": "S МН ИМ ОД",
          "active": false
        },
        {
          "index": 15,
          "word": "ли",
          "lexem": "ли",
          "tags": "S МН РОД ОД",
          "active": false
        },
        {
          "index": 16,
          "word": "ли",
          "lexem": "ли",
          "tags": "S МН ДАТ ОД",
          "active": false
        },
        {
          "index": 17,
          "word": "ли",
          "lexem": "ли",
          "tags": "S МН ВИН ОД",
          "active": false
        },
        {
          "index": 18,
          "word": "ли",
          "lexem": "ли",
          "tags": "S МН ТВОР ОД",
          "active": false
        },
        {
          "index": 19,
          "word": "ли",
          "lexem": "ли",
          "tags": "S МН ПР ОД",
          "active": false
        }
      ]
    },
    {
      "index": 2,
      "token": "он",
      "homonyms": [
        {
          "index": 0,
          "word": "он",
          "lexem": "он",
          "tags": "S ЕД МУЖ ИМ",
          "active": true
        }
      ]
    },
    {
      "index": 3,
      "token": ",",
      "homonyms": [
        {
          "index": 0,
          "word": ",",
          "lexem": ",",
          "tags": "NID",
          "active": false
        }
      ]
    },
    {
      "index": 4,
      "token": "однако",
      "homonyms": [
        {
          "index": 0,
          "word": "однако",
          "lexem": "однако",
          "tags": "CONJ",
          "active": false
        },
        {
          "index": 1,
          "word": "однако",
          "lexem": "однако",
          "tags": "INTJ",
          "active": false
        }
      ]
    },
    {
      "index": 5,
      "token": "?",
      "homonyms": [
        {
          "index": 0,
          "word": "?",
          "lexem": "?",
          "tags": "NID",
          "active": false
        }
      ]
    }
  ],
  "synts": [
    {
      "dep_type": "предик",
      "head": "проснулся",
      "dependent": "он",
      "head_i": 0,
      "head_homonym_i": 0,
      "dependent_i": 2,
      "dependent_homonym_i": 0
    }
  ]
}