{
  "sentence": "Казалось бы, какое мучение сидеть в этом чаду, в этой тесноте, среди бесконечных и непонятных разговоров и споров без всякой меры пьющих, закусывающих и пьянеющих людей!",
  "tokens": [
    "Казалось",
    "бы",
    ",",
    "какое",
    "мучение",
    "сидеть",
    "в",
    "этом",
    "чаду",
    ",",
    "в",
    "этой",
    "тесноте",
    ",",
    "среди",
    "бесконечных",
    "и",
    "непонятных",
    "разговоров",
    "и",
    "споров",
    "без",
    "всякой",
    "меры",
    "пьющих",
    ",",
    "закусывающих",
    "и",
    "пьянеющих",
    "людей",
    "!"
  ],
  "morphs": [
    {
      "index": 0,
      "token": "Казалось",
      "homonyms": [
        {
          "index": 0,
          "word": "казалось",
          "lexem": "казаться",
          "tags": "V ЕД НЕСОВ ПРОШ ИЗЪЯВ",
          "active": true
        },
        {
          "index": 1,
          "word": "казалось",
          "lexem": "казалось",
          "tags": "CONJ",
          "active": false
        }
      ]
    },
    {
      "index": 1,
      "token": "бы",
      "homonyms": [
        {
          "index": 0,
          "word": "бы",
          "lexem": "бы",
          "tags": "PART",
          "active": true
        }
      ]
    },
    {
      "index": 2,
      "token": ",",
      "homonyms": [
        {
          "index": 0,
          "word": ",",
          "lexem": ",",
          "tags": "NID",
          "active": false
        }
      ]
    },
    {
      "index": 3,
      "token": "какое",
      "homonyms": [
        {
          "index": 0,
          "word": "какое",
          "lexem": "какой",
          "tags": "A ЕД СР ВИН",
          "active": true
        },
        {
          "index": 1,
          "word": "какое",
          "lexem": "какой",
          "tags": "A ЕД СР ИМ",
          "active": true
        }
      ]
    },
    {
      "index": 4,
      "token": "мучение",
      "homonyms": [
        {
          "index": 0,
          "word": "мучение",
          "lexem": "мучение",
          "tags": "S ЕД СР ИМ НЕОД",
          "active": true
        },
        {
          "index": 1,
          "word": "мучение",
          "lexem": "мучение",
          "tags": "S ЕД СР ВИН НЕОД",
          "active": false
        }
      ]
    },
    {
      "index": 5,
      "token": "сидеть",
      "homonyms": [
        {
          "index": 0,
          "word": "сидеть",
          "lexem": "сидеть",
          "tags": "V ИНФ НЕСОВ",
          "active": true
        }
      ]
    },
    {
      "index": 6,
      "token": "в",
      "homonyms": [
        {
          "index": 0,
          "word": "в",
          "lexem": "в",
          "tags": "PR",
          "active": true
        },
        {
          "index": 1,
          "word": "в",
          "lexem": "в",
          "tags": "S ЕД МУЖ РОД НЕОД",
          "active": false
        },
        {
          "index": 2,
          "word": "в",
          "lexem": "в",
          "tags": "S ЕД МУЖ ПР НЕОД",
          "active": false
        },
        {
          "index": 3,
          "word": "в",
          "lexem": "в",
          "tags": "S ЕД МУЖ ИМ НЕОД",
          "active": false
        },
        {
          "index": 4,
          "word": "в",
          "lexem": "в",
          "tags": "S ЕД МУЖ ДАТ НЕОД",
          "active": false
        },
        {
          "index": 5,
          "word": "в",
          "lexem": "в",
          "tags": "S ЕД МУЖ ВИН НЕОД",
          "active": false
        },
        {
          "index": 6,
          "word": "в",
          "lexem": "в",
          "tags": "S ЕД МУЖ ТВОР НЕОД",
          "active": false
        },
        {
          "index": 7,
          "word": "в",
          "lexem": "в",
          "tags": "S МН МУЖ ИМ НЕОД",
          "active": false
        },
        {
          "index": 8,
          "word": "в",
          "lexem": "в",
          "tags": "S МН МУЖ РОД НЕОД",
          "active": false
        },
        {
          "index": 9,
          "word": "в",
          "lexem": "в",
          "tags": "S МН МУЖ ДАТ НЕОД",
          "active": false
        },
        {
          "index": 10,
          "word": "в",
          "lexem": "в",
          "tags": "S МН МУЖ ВИН НЕОД",
          "active": false
        },
        {
          "index": 11,
          "word": "в",
          "lexem": "в",
          "tags": "S МН МУЖ ТВОР НЕОД",
          "active": false
        },
        {
          "index": 12,
          "word": "в",
          "lexem": "в",
          "tags": "S МН МУЖ ПР НЕОД",
          "active": false
        }
      ]
    },
    {
      "index": 7,
      "token": "этом",
      "homonyms": [
        {
          "index": 0,
          "word": "этом",
          "lexem": "это",
          "tags": "S ЕД СР ПР",
          "active": true
        },
        {
          "index": 1,
          "word": "этом",
          "lexem": "этот",
          "tags": "A ЕД МУЖ ПР",
          "active": false
        },
        {
          "index": 2,
          "word": "этом",
          "lexem": "этот",
          "tags": "A ЕД СР ПР",
          "active": false
        }
      ]
    },
    {
      "index": 8,
      "token": "чаду",
      "homonyms": [
        {
          "index": 0,
          "word": "чаду",
          "lexem": "чадо",
          "tags": "S ЕД СР ДАТ ОД",
          "active": false
        },
        {
          "index": 1,
          "word": "чаду",
          "lexem": "чад",
          "tags": "S ЕД МУЖ МЕСТН НЕОД",
          "active": false
        },
        {
          "index": 2,
          "word": "чаду",
          "lexem": "чад",
          "tags": "S ЕД МУЖ ДАТ НЕОД",
          "active": false
        },
        {
          "index": 3,
          "word": "чаду",
          "lexem": "чад",
          "tags": "S ЕД МУЖ ПАРТ НЕОД",
          "active": false
        },
        {
          "index": 4,
          "word": "чаду",
          "lexem": "чад",
          "tags": "S ЕД МУЖ ДАТ НЕОД",
          "active": false
        }
      ]
    },
    {
      "index": 9,
      "token": ",",
      "homonyms": [
        {
          "index": 0,
          "word": ",",
          "lexem": ",",
          "tags": "NID",
          "active": false
        }
      ]
    },
    {
      "index": 10,
      "token": "в",
      "homonyms": [
        {
          "index": 0,
          "word": "в",
          "lexem": "в",
          "tags": "PR",
          "active": true
        },
        {
          "index": 1,
          "word": "в",
          "lexem": "в",
          "tags": "S ЕД МУЖ РОД НЕОД",
          "active": false
        },
        {
          "index": 2,
          "word": "в",
          "lexem": "в",
          "tags": "S ЕД МУЖ ПР НЕОД",
          "active": false
        },
        {
          "index": 3,
          "word": "в",
          "lexem": "в",
          "tags": "S ЕД МУЖ ИМ НЕОД",
          "active": false
        },
        {
          "index": 4,
          "word": "в",
          "lexem": "в",
          "tags": "S ЕД МУЖ ДАТ НЕОД",
          "active": false
        },
        {
          "index": 5,
          "word": "в",
          "lexem": "в",
          "tags": "S ЕД МУЖ ВИН НЕОД",
          "active": false
        },
        {
          "index": 6,
          "word": "в",
          "lexem": "в",
          "tags": "S ЕД МУЖ ТВОР НЕОД",
          "active": false
        },
        {
          "index": 7,
          "word": "в",
          "lexem": "в",
          "tags": "S МН МУЖ ИМ НЕОД",
          "active": false
        },
        {
          "index": 8,
          "word": "в",
          "lexem": "в",
          "tags": "S МН МУЖ РОД НЕОД",
          "active": false
        },
        {
          "index": 9,
          "word": "в",
          "lexem": "в",
          "tags": "S МН МУЖ ДАТ НЕОД",
          "active": false
        },
        {
          "index": 10,
          "word": "в",
          "lexem": "в",
          "tags": "S МН МУЖ ВИН НЕОД",
          "active": false
        },
        {
          "index": 11,
          "word": "в",
          "lexem": "в",
          "tags": "S МН МУЖ ТВОР НЕОД",
          "active": false
        },
        {
          "index": 12,
          "word": "в",
          "lexem": "в",
          "tags": "S МН МУЖ ПР НЕОД",
          "active": false
        }
      ]
    },
    {
      "index": 11,
      "token": "этой",
      "homonyms": [
        {
          "index": 0,
          "word": "этой",
          "lexem": "этот",
          "tags": "A ЕД ЖЕН РОД",
          "active": false
        },
        {
          "index": 1,
          "word": "этой",
          "lexem": "этот",
          "tags": "A ЕД ЖЕН ПР",
          "active": true
        },
        {
          "index": 2,
          "word": "этой",
          "lexem": "этот",
          "tags": "A ЕД ЖЕН ТВОР",
          "active": false
        },
        {
          "index": 3,
          "word": "этой",
          "lexem": "этот",
          "tags": "A ЕД ЖЕН ДАТ",
          "active": true
        }
      ]
    },
    {
      "index": 12,
      "token": "тесноте",
      "homonyms": [
        {
          "index": 0,
          "word": "тесноте",
          "lexem": "теснота",
          "tags": "S ЕД ЖЕН ДАТ НЕОД",
          "active": true
        },
        {
          "index": 1,
          "word": "тесноте",
          "lexem": "теснота",
          "tags": "S ЕД ЖЕН ПР НЕОД",
          "active": true
        }
      ]
    },
    {
      "index": 13,
      "token": ",",
      "homonyms": [
        {
          "index": 0,
          "word": ",",
          "lexem": ",",
          "tags": "NID",
          "active": false
        }
      ]
    },
    {
      "index": 14,
      "token": "среди",
      "homonyms": [
        {
          "index": 0,
          "word": "среди",
          "lexem": "среди",
          "tags": "PR",
          "active": true
        }
      ]
    },
    {
      "index": 15,
      "token": "бесконечных",
      "homonyms": [
        {
          "index": 0,
          "word": "бесконечных",
          "lexem": "бесконечный",
          "tags": "A МН РОД",
          "active": true
        },
        {
          "index": 1,
          "word": "бесконечных",
          "lexem": "бесконечный",
          "tags": "A МН ВИН",
          "active": false
        },
        {
          "index": 2,
          "word": "бесконечных",
          "lexem": "бесконечный",
          "tags": "A МН ПР",
          "active": false
        }
      ]
    },
    {
      "index": 16,
      "token": "и",
      "homonyms": [
        {
          "index": 0,
          "word": "и",
          "lexem": "и",
          "tags": "CONJ",
          "active": true
        },
        {
          "index": 1,
          "word": "и",
          "lexem": "и",
          "tags": "PART",
          "active": false
        },
        {
          "index": 2,
          "word": "и",
          "lexem": "и",
          "tags": "INTJ",
          "active": false
        },
        {
          "index": 3,
          "word": "и",
          "lexem": "и",
          "tags": "S ЕД МУЖ ИМ ОД",
          "active": false
        },
        {
          "index": 4,
          "word": "и",
          "lexem": "и",
          "tags": "S ЕД МУЖ РОД ОД",
          "active": false
        },
        {
          "index": 5,
          "word": "и",
          "lexem": "и",
          "tags": "S ЕД МУЖ ДАТ ОД",
          "active": false
        },
        {
          "index": 6,
          "word": "и",
          "lexem": "и",
          "tags": "S ЕД МУЖ ВИН ОД",
          "active": false
        },
        {
          "index": 7,
          "word": "и",
          "lexem": "и",
          "tags": "S ЕД МУЖ ТВОР ОД",
          "active": false
        },
        {
          "index": 8,
          "word": "и",
          "lexem": "и",
          "tags": "S ЕД МУЖ ПР ОД",
          "active": false
        },
        {
          "index": 9,
          "word": "и",
          "lexem": "и",
          "tags": "S МН МУЖ ИМ ОД",
          "active": false
        },
        {
          "index": 10,
          "word": "и",
          "lexem": "и",
          "tags": "S МН МУЖ РОД ОД",
          "active": false
        },
        {
          "index": 11,
          "word": "и",
          "lexem": "и",
          "tags": "S МН МУЖ ДАТ ОД",
          "active": false
        },
        {
          "index": 12,
          "word": "и",
          "lexem": "и",
          "tags": "S МН МУЖ ВИН ОД",
          "active": false
        },
        {
          "index": 13,
          "word": "и",
          "lexem": "и",
          "tags": "S МН МУЖ ТВОР ОД",
          "active": false
        },
        {
          "index": 14,
          "word": "и",
          "lexem": "и",
          "tags": "S МН МУЖ ПР ОД",
          "active": false
        }
      ]
    },
    {
      "index": 17,
      "token": "непонятных",
      "homonyms": [
        {
          "index": 0,
          "word": "непонятных",
          "lexem": "непонятный",
          "tags": "A МН РОД",
          "active": true
        },
        {
          "index": 1,
          "word": "непонятных",
          "lexem": "непонятный",
          "tags": "A МН ВИН",
          "active": true
        },
        {
          "index": 2,
          "word": "непонятных",
          "lexem": "непонятный",
          "tags": "A МН ПР",
          "active": false
        }
      ]
    },
    {
      "index": 18,
      "token": "разговоров",
      "homonyms": [
        {
          "index": 0,
          "word": "разговоров",
          "lexem": "разговор",
          "tags": "S МН МУЖ РОД НЕОД",
          "active": true
        }
      ]
    },
    {
      "index": 19,
      "token": "и",
      "homonyms": [
        {
          "index": 0,
          "word": "и",
          "lexem": "и",
          "tags": "CONJ",
          "active": true
        },
        {
          "index": 1,
          "word": "и",
          "lexem": "и",
          "tags": "PART",
          "active": false
        },
        {
          "index": 2,
          "word": "и",
          "lexem": "и",
          "tags": "INTJ",
          "active": false
        },
        {
          "index": 3,
          "word": "и",
          "lexem": "и",
          "tags": "S ЕД МУЖ ИМ ОД",
          "active": false
        },
        {
          "index": 4,
          "word": "и",
          "lexem": "и",
          "tags": "S ЕД МУЖ РОД ОД",
          "active": false
        },
        {
          "index": 5,
          "word": "и",
          "lexem": "и",
          "tags": "S ЕД МУЖ ДАТ ОД",
          "active": false
        },
        {
          "index": 6,
          "word": "и",
          "lexem": "и",
          "tags": "S ЕД МУЖ ВИН ОД",
          "active": false
        },
        {
          "index": 7,
          "word": "и",
          "lexem": "и",
          "tags": "S ЕД МУЖ ТВОР ОД",
          "active": false
        },
        {
          "index": 8,
          "word": "и",
          "lexem": "и",
          "tags": "S ЕД МУЖ ПР ОД",
          "active": false
        },
        {
          "index": 9,
          "word": "и",
          "lexem": "и",
          "tags": "S МН МУЖ ИМ ОД",
          "active": false
        },
        {
          "index": 10,
          "word": "и",
          "lexem": "и",
          "tags": "S МН МУЖ РОД ОД",
          "active": false
        },
        {
          "index": 11,
          "word": "и",
          "lexem": "и",
          "tags": "S МН МУЖ ДАТ ОД",
          "active": false
        },
        {
          "index": 12,
          "word": "и",
          "lexem": "и",
          "tags": "S МН МУЖ ВИН ОД",
          "active": false
        },
        {
          "index": 13,
          "word": "и",
          "lexem": "и",
          "tags": "S МН МУЖ ТВОР ОД",
          "active": false
        },
        {
          "index": 14,
          "word": "и",
          "lexem": "и",
          "tags": "S МН МУЖ ПР ОД",
          "active": false
        }
      ]
    },
    {
      "index": 20,
      "token": "споров",
      "homonyms": [
        {
          "index": 0,
          "word": "споров",
          "lexem": "спор",
          "tags": "S МН МУЖ РОД НЕОД",
          "active": false
        },
        {
          "index": 1,
          "word": "споров",
          "lexem": "спороть",
          "tags": "V ДЕЕПР СОВ ПРОШ",
          "active": true
        }
      ]
    },
    {
      "index": 21,
      "token": "без",
      "homonyms": [
        {
          "index": 0,
          "word": "без",
          "lexem": "без",
          "tags": "PR",
          "active": true
        }
      ]
    },
    {
      "index": 22,
      "token": "всякой",
      "homonyms": [
        {
          "index": 0,
          "word": "всякой",
          "lexem": "всякий",
          "tags": "A ЕД ЖЕН РОД",
          "active": true
        },
        {
          "index": 1,
          "word": "всякой",
          "lexem": "всякий",
          "tags": "A ЕД ЖЕН ТВОР",
          "active": false
        },
        {
          "index": 2,
          "word": "всякой",
          "lexem": "всякая",
          "tags": "S ЕД ЖЕН РОД",
          "active": true
        },
        {
          "index": 3,
          "word": "всякой",
          "lexem": "всякая",
          "tags": "S ЕД ЖЕН ДАТ",
          "active": false
        },
        {
          "index": 4,
          "word": "всякой",
          "lexem": "всякая",
          "tags": "S ЕД ЖЕН ТВОР",
          "active": false
        },
        {
          "index": 5,
          "word": "всякой",
          "lexem": "всякая",
          "tags": "S ЕД ЖЕН ПР",
          "active": false
        },
        {
          "index": 6,
          "word": "всякой",
          "lexem": "всякий",
          "tags": "A ЕД ЖЕН ДАТ",
          "active": false
        },
        {
          "index": 7,
          "word": "всякой",
          "lexem": "всякий",
          "tags": "A ЕД ЖЕН ПР",
          "active": false
        }
      ]
    },
    {
      "index": 23,
      "token": "меры",
      "homonyms": [
        {
          "index": 0,
          "word": "меры",
          "lexem": "мера",
          "tags": "S МН ЖЕН ВИН НЕОД",
          "active": false
        },
        {
          "index": 1,
          "word": "меры",
          "lexem": "мера",
          "tags": "S МН ЖЕН ИМ НЕОД",
          "active": false
        },
        {
          "index": 2,
          "word": "меры",
          "lexem": "мера",
          "tags": "S ЕД ЖЕН РОД НЕОД",
          "active": true
        }
      ]
    },
    {
      "index": 24,
      "token": "пьющих",
      "homonyms": [
        {
          "index": 0,
          "word": "пьющих",
          "lexem": "пьющий",
          "tags": "A МН РОД",
          "active": true
        },
        {
          "index": 1,
          "word": "пьющих",
          "lexem": "пьющий",
          "tags": "A МН ВИН",
          "active": true
        },
        {
          "index": 2,
          "word": "пьющих",
          "lexem": "пьющий",
          "tags": "A МН ПР",
          "active": false
        },
        {
          "index": 3,
          "word": "пьющих",
          "lexem": "пить",
          "tags": "V ПРИЧ МН РОД НЕПРОШ",
          "active": false
        },
        {
          "index": 4,
          "word": "пьющих",
          "lexem": "пить",
          "tags": "V ПРИЧ МН ВИН НЕПРОШ",
          "active": false
        },
        {
          "index": 5,
          "word": "пьющих",
          "lexem": "пить",
          "tags": "V ПРИЧ МН ПР НЕПРОШ",
          "active": false
        }
      ]
    },
    {
      "index": 25,
      "token": ",",
      "homonyms": [
        {
          "index": 0,
          "word": ",",
          "lexem": ",",
          "tags": "NID",
          "active": false
        }
      ]
    },
    {
      "index": 26,
      "token": "закусывающих",
      "homonyms": [
        {
          "index": 0,
          "word": "закусывающих",
          "lexem": "закусывать",
          "tags": "V ПРИЧ МН РОД НЕПРОШ",
          "active": true
        },
        {
          "index": 1,
          "word": "закусывающих",
          "lexem": "закусывать",
          "tags": "V ПРИЧ МН ВИН НЕПРОШ",
          "active": true
        },
        {
          "index": 2,
          "word": "закусывающих",
          "lexem": "закусывать",
          "tags": "V ПРИЧ МН ПР НЕПРОШ",
          "active": true
        }
      ]
    },
    {
      "index": 27,
      "token": "и",
      "homonyms": [
        {
          "index": 0,
          "word": "и",
          "lexem": "и",
          "tags": "CONJ",
          "active": true
        },
        {
          "index": 1,
          "word": "и",
          "lexem": "и",
          "tags": "PART",
          "active": false
        },
        {
          "index": 2,
          "word": "и",
          "lexem": "и",
          "tags": "INTJ",
          "active": false
        },
        {
          "index": 3,
          "word": "и",
          "lexem": "и",
          "tags": "S ЕД МУЖ ИМ ОД",
          "active": false
        },
        {
          "index": 4,
          "word": "и",
          "lexem": "и",
          "tags": "S ЕД МУЖ РОД ОД",
          "active": false
        },
        {
          "index": 5,
          "word": "и",
          "lexem": "и",
          "tags": "S ЕД МУЖ ДАТ ОД",
          "active": false
        },
        {
          "index": 6,
          "word": "и",
          "lexem": "и",
          "tags": "S ЕД МУЖ ВИН ОД",
          "active": false
        },
        {
          "index": 7,
          "word": "и",
          "lexem": "и",
          "tags": "S ЕД МУЖ ТВОР ОД",
          "active": false
        },
        {
          "index": 8,
          "word": "и",
          "lexem": "и",
          "tags": "S ЕД МУЖ ПР ОД",
          "active": false
        },
        {
          "index": 9,
          "word": "и",
          "lexem": "и",
          "tags": "S МН МУЖ ИМ ОД",
          "active": false
        },
        {
          "index": 10,
          "word": "и",
          "lexem": "и",
          "tags": "S МН МУЖ РОД ОД",
          "active": false
        },
        {
          "index": 11,
          "word": "и",
          "lexem": "и",
          "tags": "S МН МУЖ ДАТ ОД",
          "active": false
        },
        {
          "index": 12,
          "word": "и",
          "lexem": "и",
          "tags": "S МН МУЖ ВИН ОД",
          "active": false
        },
        {
          "index": 13,
          "word": "и",
          "lexem": "и",
          "tags": "S МН МУЖ ТВОР ОД",
          "active": false
        },
        {
          "index": 14,
          "word": "и",
          "lexem": "и",
          "tags": "S МН МУЖ ПР ОД",
          "active": false
        }
      ]
    },
    {
      "index": 28,
      "token": "пьянеющих",
      "homonyms": [
        {
          "index": 0,
          "word": "пьянеющих",
          "lexem": "пьянеть",
          "tags": "V ПРИЧ МН РОД НЕПРОШ",
          "active": true
        },
        {
          "index": 1,
          "word": "пьянеющих",
          "lexem": "пьянеть",
          "tags": "V ПРИЧ МН ВИН НЕПРОШ",
          "active": true
        },
        {
          "index": 2,
          "word": "пьянеющих",
          "lexem": "пьянеть",
          "tags": "V ПРИЧ МН ПР НЕПРОШ",
          "active": false
        }
      ]
    },
    {
      "index": 29,
      "token": "людей",
      "homonyms": [
        {
          "index": 0,
          "word": "людей",
          "lexem": "человек",
          "tags": "S МН МУЖ РОД ОД",
          "active": true
        },
        {
          "index": 1,
          "word": "людей",
          "lexem": "человек",
          "tags": "S МН МУЖ ВИН ОД",
          "active": true
        }
      ]
    },
    {
      "index": 30,
      "token": "!",
      "homonyms": [
        {
          "index": 0,
          "word": "!",
          "lexem": "!",
          "tags": "NID",
          "active": false
        }
      ]
    }
  ],
  "synts": [
    {
      "dep_type": "опред",
      "head": "разговоров",
      "dependent": "непонятных",
      "head_i": 18,
      "head_homonym_i": 0,
      "dependent_i": 17,
      "dependent_homonym_i": 0
    },
    {
      "dep_type": "опред",
      "head": "людей",
      "dependent": "пьянеющих",
      "head_i": 29,
      "head_homonym_i": 0,
      "dependent_i": 28,
      "dependent_homonym_i": 0
    },
    {
      "dep_type": "опред",
      "head": "людей",
      "dependent": "пьянеющих",
      "head_i": 29,
      "head_homonym_i": 1,
      "dependent_i": 28,
      "dependent_homonym_i": 1
    },
    {
      "dep_type": "опред",
      "head": "мучение",
      "dependent": "какое",
      "head_i": 4,
      "head_homonym_i": 0,
      "dependent_i": 3,
      "dependent_homonym_i": 1
    },
    {
      "dep_type": "опред",
      "head": "тесноте",
      "dependent": "этой",
      "head_i": 12,
      "head_homonym_i": 0,
      "dependent_i": 11,
      "dependent_homonym_i": 3
    },
    {
      "dep_type": "опред",
      "head": "тесноте",
      "dependent": "этой",
      "head_i": 12,
      "head_homonym_i": 1,
      "dependent_i": 11,
      "dependent_homonym_i": 1
    },
    {
      "dep_type": "опред",
      "head": "меры",
      "dependent": "всякой",
      "head_i": 23,
      "head_homonym_i": 2,
      "dependent_i": 22,
      "dependent_homonym_i": 0
    },
    {
      "dep_type": "предл",
      "head": "в",
      "dependent": "этом",
      "head_i": 6,
      "head_homonym_i": 0,
      "dependent_i": 7,
      "dependent_homonym_i": 0
    },
    {
      "dep_type": "предл",
      "head": "в",
      "dependent": "тесноте",
      "head_i": 10,
      "head_homonym_i": 0,
      "dependent_i": 12,
      "dependent_homonym_i": 1
    },
    {
      "dep_type": "предл",
      "head": "без",
      "dependent": "всякой",
      "head_i": 21,
      "head_homonym_i": 0,
      "dependent_i": 22,
      "dependent_homonym_i": 2
    },
    {
      "dep_type": "обст",
      "head": "сидеть",
      "dependent": "споров",
      "head_i": 5,
      "head_homonym_i": 0,
      "dependent_i": 20,
      "dependent_homonym_i": 1
    },
    {
      "dep_type": "аналит",
      "head": "казалось",
      "dependent": "бы",
      "head_i": 0,
      "head_homonym_i": 0,
      "dependent_i": 1,
      "dependent_homonym_i": 0
    },
    {
      "dep_type": "предик",
      "head": "казалось",
      "dependent": "мучение",
      "head_i": 0,
      "head_homonym_i": 0,
      "dependent_i": 4,
      "dependent_homonym_i": 0
    },
    {
      "dep_type": "1-компл",
      "head": "сидеть",
      "dependent": "в",
      "head_i": 5,
      "head_homonym_i": 0,
      "dependent_i": 6,
      "dependent_homonym_i": 0
    },
    {
      "dep_type": "1-компл",
      "head": "сидеть",
      "dependent": "в",
      "head_i": 5,
      "head_homonym_i": 0,
      "dependent_i": 10,
      "dependent_homonym_i": 0
    },
    {
      "dep_type": "1-компл",
      "head": "сидеть",
      "dependent": "тесноте",
      "head_i": 5,
      "head_homonym_i": 0,
      "dependent_i": 12,
      "dependent_homonym_i": 0
    },
    {
      "dep_type": "1-компл",
      "head": "сидеть",
      "dependent": "среди",
      "head_i": 5,
      "head_homonym_i": 0,
      "dependent_i": 14,
      "dependent_homonym_i": 0
    },
    {
      "dep_type": "1-компл",
      "head": "закусывающих",
      "dependent": "людей",
      "head_i": 26,
      "head_homonym_i": 0,
      "dependent_i": 29,
      "dependent_homonym_i": 1
    },
    {
      "dep_type": "1-компл",
      "head": "закусывающих",
      "dependent": "людей",
      "head_i": 26,
      "head_homonym_i": 1,
      "dependent_i": 29,
      "dependent_homonym_i": 1
    },
    {
      "dep_type": "1-компл",
      "head": "закусывающих",
      "dependent": "людей",
      "head_i": 26,
      "head_homonym_i": 2,
      "dependent_i": 29,
      "dependent_homonym_i": 1
    },
    {
      "dep_type": "соч-союзн",
      "head": "и",
      "dependent": "непонятных",
      "head_i": 16,
      "head_homonym_i": 0,
      "dependent_i": 17,
      "dependent_homonym_i": 0
    },
    {
      "dep_type": "соч-союзн",
      "head": "и",
      "dependent": "непонятных",
      "head_i": 16,
      "head_homonym_i": 0,
      "dependent_i": 17,
      "dependent_homonym_i": 1
    },
    {
      "dep_type": "соч-союзн",
      "head": "и",
      "dependent": "разговоров",
      "head_i": 16,
      "head_homonym_i": 0,
      "dependent_i": 18,
      "dependent_homonym_i": 0
    },
    {
      "dep_type": "соч-союзн",
      "head": "и",
      "dependent": "всякой",
      "head_i": 19,
      "head_homonym_i": 0,
      "dependent_i": 22,
      "dependent_homonym_i": 0
    },
    {
      "dep_type": "соч-союзн",
      "head": "и",
      "dependent": "всякой",
      "head_i": 19,
      "head_homonym_i": 0,
      "dependent_i": 22,
      "dependent_homonym_i": 2
    },
    {
      "dep_type": "соч-союзн",
      "head": "и",
      "dependent": "меры",
      "head_i": 19,
      "head_homonym_i": 0,
      "dependent_i": 23,
      "dependent_homonym_i": 2
    },
    {
      "dep_type": "соч-союзн",
      "head": "и",
      "dependent": "пьющих",
      "head_i": 19,
      "head_homonym_i": 0,
      "dependent_i": 24,
      "dependent_homonym_i": 0
    },
    {
      "dep_type": "соч-союзн",
      "head": "и",
      "dependent": "пьющих",
      "head_i": 19,
      "head_homonym_i": 0,
      "dependent_i": 24,
      "dependent_homonym_i": 1
    },
    {
      "dep_type": "соч-союзн",
      "head": "и",
      "dependent": "людей",
      "head_i": 27,
      "head_homonym_i": 0,
      "dependent_i": 29,
      "dependent_homonym_i": 0
    },
    {
      "dep_type": "соч-союзн",
      "head": "и",
      "dependent": "людей",
      "head_i": 27,
      "head_homonym_i": 0,
      "dependent_i": 29,
      "dependent_homonym_i": 1
    },
    {
      "dep_type": "сочин",
      "head": "бесконечных",
      "dependent": "и",
      "head_i": 15,
      "head_homonym_i": 0,
      "dependent_i": 16,
      "dependent_homonym_i": 0
    },
    {
      "dep_type": "сочин",
      "head": "разговоров",
      "dependent": "и",
      "head_i": 18,
      "head_homonym_i": 0,
      "dependent_i": 19,
      "dependent_homonym_i": 0
    },
    {
      "dep_type": "обст",
      "head": "сидеть",
      "dependent": "в",
      "head_i": 5,
      "head_homonym_i": 0,
      "dependent_i": 6,
      "dependent_homonym_i": 0
    },
    {
      "dep_type": "обст",
      "head": "споров",
      "dependent": "среди",
      "head_i": 20,
      "head_homonym_i": 1,
      "dependent_i": 14,
      "dependent_homonym_i": 0
    },
    {
      "dep_type": "обст",
      "head": "споров",
      "dependent": "без",
      "head_i": 20,
      "head_homonym_i": 1,
      "dependent_i": 21,
      "dependent_homonym_i": 0
    },
    {
      "dep_type": "обст",
      "head": "казалось",
      "dependent": "сидеть",
      "head_i": 0,
      "head_homonym_i": 0,
      "dependent_i": 5,
      "dependent_homonym_i": 0
    }
  ]
}